cdk_cross_account_route53/__init__.py
cdk_cross_account_route53/py.typed
cdk_cross_account_route53/_jsii/__init__.py
cdk_cross_account_route53/_jsii/cdk-cross-account-route53@1.0.3.jsii.tgz
cdk_cross_account_route53-1.0.3.dist-info/LICENSE
cdk_cross_account_route53-1.0.3.dist-info/METADATA
cdk_cross_account_route53-1.0.3.dist-info/WHEEL
cdk_cross_account_route53-1.0.3.dist-info/top_level.txt
cdk_cross_account_route53-1.0.3.dist-info/RECORD
