Metadata-Version: 2.1
Name: cdk-cross-account-route53
Version: 1.0.3
Summary: CDK Construct to allow creation of Route 53 records in a different account
Home-page: https://github.com/johnf/cdk-cross-account-route53.git
Author: John Ferlito<johnf@inodes.org>
License: Apache-2.0
Project-URL: Source, https://github.com/johnf/cdk-cross-account-route53.git
Classifier: Intended Audience :: Developers
Classifier: Operating System :: OS Independent
Classifier: Programming Language :: JavaScript
Classifier: Programming Language :: Python :: 3 :: Only
Classifier: Programming Language :: Python :: 3.9
Classifier: Programming Language :: Python :: 3.10
Classifier: Programming Language :: Python :: 3.11
Classifier: Typing :: Typed
Classifier: Development Status :: 5 - Production/Stable
Classifier: License :: OSI Approved
Requires-Python: ~=3.9
License-File: LICENSE
Requires-Dist: aws-cdk-lib <3.0.0,>=2.146.0
Requires-Dist: constructs <11.0.0,>=10.0.5
Requires-Dist: jsii <2.0.0,>=1.114.1
Requires-Dist: publication >=0.0.3
Requires-Dist: typeguard <4.3.0,>=2.13.3
